stringlifier/__init__.py
stringlifier/api.py
stringlifier/modules/__init__.py
stringlifier/modules/stringc.py
stringlifier/modules/stringc2.py
stringlifier/modules/training.py
stringlifier_ported-0.2.dist-info/LICENSE
stringlifier_ported-0.2.dist-info/METADATA
stringlifier_ported-0.2.dist-info/WHEEL
stringlifier_ported-0.2.dist-info/top_level.txt
stringlifier_ported-0.2.dist-info/RECORD
