Metadata-Version: 2.1
Name: stringlifier-ported
Version: 0.2
Summary: Python module for detecting password, api keys hashes and any other string that resembles a randomly generated character sequence. Originated from https://github.com/adobe/stringlifier, this package updated dependencies for up to date python versions
Home-page: https://github.com/isu-kim/stringlifier
Author: Multiple authors
Author-email: tiberiu44@gmail.com
License: UNKNOWN
Platform: UNKNOWN
Classifier: Programming Language :: Python :: 3.0
Classifier: License :: OSI Approved :: Apache Software License
Classifier: Operating System :: OS Independent
License-File: LICENSE
Requires-Dist: ipdb ==0.13.4
Requires-Dist: nptyping ==1.3.0
Requires-Dist: numpy ==1.22.0
Requires-Dist: PyJWT ==1.7.1
Requires-Dist: torch ==1.13.1
Requires-Dist: tqdm ==4.50.2
